thresecdsa/__init__.py
thresecdsa/__main__.py
thresecdsa/curves.py
thresecdsa/ecdsa.py
thresecdsa/eddsa.py
thresecdsa/rand.py
thresecdsa/shamir.py
thresecdsa/serialization/__init__.py
thresecdsa/serialization/ecdsa.py
thresecdsa/serialization/eddsa.py
thresecdsa/serialization/serialization.py
thresecdsa-0.1.1.dist-info/LICENSE
thresecdsa-0.1.1.dist-info/METADATA
thresecdsa-0.1.1.dist-info/WHEEL
thresecdsa-0.1.1.dist-info/entry_points.txt
thresecdsa-0.1.1.dist-info/top_level.txt
thresecdsa-0.1.1.dist-info/RECORD
