Metadata-Version: 2.1
Name: thresecdsa
Version: 0.1.1
Summary: An implementation of MPC threshold signatures
Author: vis
Author-email: vishleshakee@gmail.com
License: GPL-3.0-orlater
Requires-Python: >=3.8
License-File: LICENSE
Requires-Dist: base58
Requires-Dist: ecdsa (>=0.17.0)
Requires-Dist: phe
Requires-Dist: pycryptodome
